fsps-0.4.7.dist-info/RECORD
fsps-0.4.7.dist-info/WHEEL
fsps-0.4.7.dist-info/METADATA
fsps-0.4.7.dist-info/licenses/LICENSE.rst
fsps-0.4.7.dist-info/licenses/AUTHORS.rst
fsps/CMakeLists.txt
fsps/fsps.f90
fsps/sps_home.py
fsps/__init__.py
fsps/fsps_version.py
fsps/_fsps.cpython-310-darwin.so
fsps/filters.py
fsps/fsps.py
fsps/.dylibs/libgfortran.5.dylib
fsps/.dylibs/libquadmath.0.dylib
fsps/.dylibs/libgcc_s.1.1.dylib
fsps/libfsps/LICENSE
fsps/libfsps/src/imf_weight.f90
fsps/libfsps/src/write_isochrone.f90
fsps/libfsps/src/sfhinfo.f90
fsps/libfsps/src/add_bs.f90
fsps/libfsps/src/lesssimple.f90
fsps/libfsps/src/pz_convol.f90
fsps/libfsps/src/compsp.f90
fsps/libfsps/src/simple.f90
fsps/libfsps/src/add_xrb.f90
fsps/libfsps/src/tsum.f90
fsps/libfsps/src/getindx.f90
fsps/libfsps/src/csp_gen.f90
fsps/libfsps/src/sps_vars.f90
fsps/libfsps/src/locate.f90
fsps/libfsps/src/get_lumdist.f90
fsps/libfsps/src/sbf.f90
fsps/libfsps/src/autosps.f90
fsps/libfsps/src/vacairconv.f90
fsps/libfsps/src/mod_hb.f90
fsps/libfsps/src/add_remnants.f90
fsps/libfsps/src/agn_dust.f90
fsps/libfsps/src/attn_curve.f90
fsps/libfsps/src/sfhlimit.f90
fsps/libfsps/src/spec_bin.f90
fsps/libfsps/src/mod_gb.f90
fsps/libfsps/src/linterp.f90
fsps/libfsps/src/add_dust.f90
fsps/libfsps/src/setup_tabular_sfh.f90
fsps/libfsps/src/add_agb_dust.f90
fsps/libfsps/src/sps_setup.f90
fsps/libfsps/src/funcint.f90
fsps/libfsps/src/getspec.f90
fsps/libfsps/src/igm_absorb.f90
fsps/libfsps/src/smoothspec.f90
fsps/libfsps/src/sps_utils.f90
fsps/libfsps/src/getmags.f90
fsps/libfsps/src/sfh_weight.f90
fsps/libfsps/src/ssp_gen.f90
fsps/libfsps/src/ztinterp.f90
fsps/libfsps/src/imf.f90
fsps/libfsps/src/get_tuniv.f90
fsps/libfsps/src/sfhstat.f90
fsps/libfsps/src/linterparr.f90
fsps/libfsps/src/add_nebular.f90
fsps/libfsps/src/intsfwght.f90
