Metadata-Version: 2.1
Name: fsps
Version: 0.4.7
Summary: Python bindings for Charlie Conroy's FSPS
Author-Email: Dan Foreman-Mackey <foreman.mackey@gmail.com>
License: MIT License
Classifier: Development Status :: 5 - Production/Stable
Classifier: Intended Audience :: Developers
Classifier: Intended Audience :: Science/Research
Classifier: License :: OSI Approved :: MIT License
Classifier: Operating System :: OS Independent
Classifier: Programming Language :: Python
Project-URL: Homepage, https://dfm.io/python-fsps
Project-URL: Source, https://github.com/dfm/python-fsps
Project-URL: Bug tracker, https://github.com/dfm/python-fsps/issues
Requires-Python: >=3.9
Requires-Dist: numpy
Requires-Dist: pytest; extra == "test"
Requires-Dist: pytest-xdist; extra == "test"
Provides-Extra: test
